akeru/__init__.py
akeru/admin.py
akeru/app_settings.py
akeru/apps.py
akeru/deploy.py
akeru/models.py
akeru/urls.py
akeru/views.py
akeru/libs/__init__.py
akeru/libs/access.py
akeru/libs/console.py
akeru/libs/setting.py
akeru/migrations/0001_initial.py
akeru/migrations/__init__.py
akeru/static/css/bootstrap-grid.css
akeru/static/css/bootstrap-grid.min.css
akeru/static/css/bootstrap-reboot.css
akeru/static/css/bootstrap-reboot.min.css
akeru/static/css/bootstrap.css
akeru/static/css/bootstrap.min.css
akeru/static/img/iam.png
akeru/static/img/roles.PNG
akeru/static/js/bootstrap.min.js
akeru/static/js/jquery-3.5.1.min.js
akeru/templates/akeru/access.html
akeru/templates/akeru/base.html
akeru/templates/akeru/index.html
akeru_cloud_access-0.0.2.dist-info/LICENSE
akeru_cloud_access-0.0.2.dist-info/METADATA
akeru_cloud_access-0.0.2.dist-info/WHEEL
akeru_cloud_access-0.0.2.dist-info/top_level.txt
akeru_cloud_access-0.0.2.dist-info/RECORD
