Metadata-Version: 2.1
Name: akeru-cloud-access
Version: 0.0.2
Summary: A Django package that supports creation of IAM users/roles and allows federated access via Django users/groups
Home-page: https://github.com/astrix37/akeru-cloud-access
Author: Alexander Colvin
Author-email: alexander.colvin@hotmail.com
License: UNKNOWN
Platform: UNKNOWN
Classifier: Programming Language :: Python :: 3
Classifier: License :: OSI Approved :: GNU General Public License v3 (GPLv3)
Classifier: Operating System :: OS Independent
Requires-Python: >=3.6
Requires-Dist: django (>=3.0)
Requires-Dist: boto3 (>=1.14.60)
Requires-Dist: requests (>=2.24.0)
Requires-Dist: tox
